inferia/__init__.py
inferia/cli.py
inferia/cli_init.py
inferia/debug_auth.py
inferia/inferiadocs.py
inferia/startup_events.py
inferia/startup_ui.py
inferia/dashboard/Logo.png
inferia/dashboard/index.html
inferia/dashboard/logo.svg
inferia/dashboard/vite.svg
inferia/dashboard/assets/index-DUlwZIu5.css
inferia/dashboard/assets/index-DxQYBWSj.js
inferia/gateways/filtration_gateway/app.py
inferia/gateways/filtration_gateway/main.py
inferia/gateways/inference_gateway/__init__.py
inferia/gateways/inference_gateway/app.py
inferia/gateways/inference_gateway/client.py
inferia/gateways/inference_gateway/config.py
inferia/gateways/inference_gateway/main.py
inferia/gateways/inference_gateway/core/auth.py
inferia/gateways/inference_gateway/core/http_client.py
inferia/gateways/inference_gateway/core/orchestrator.py
inferia/gateways/inference_gateway/core/providers.py
inferia/gateways/inference_gateway/core/rate_limiter.py
inferia/gateways/inference_gateway/core/service.py
inferia/gateways/inference_gateway/core/stream_processor.py
inferia/gateways/orchestration_gateway/app.py
inferia/gateways/orchestration_gateway/config.py
inferia/gateways/orchestration_gateway/main.py
inferia/infra/schema/global_schema.sql
inferia/infra/schema/orchestration.sql
inferia/services/filtration/bootstrap_db.py
inferia/services/filtration/config.py
inferia/services/filtration/drop_db.py
inferia/services/filtration/models.py
inferia/services/filtration/reset_db.py
inferia/services/filtration/audit/__init__.py
inferia/services/filtration/audit/api_models.py
inferia/services/filtration/audit/router.py
inferia/services/filtration/audit/service.py
inferia/services/filtration/data/__init__.py
inferia/services/filtration/data/api_models.py
inferia/services/filtration/data/chunker.py
inferia/services/filtration/data/engine.py
inferia/services/filtration/data/parser.py
inferia/services/filtration/data/router.py
inferia/services/filtration/db/__init__.py
inferia/services/filtration/db/database.py
inferiallm-1.0.7.dist-info/licenses/LICENSE
inferiallm-1.0.7.dist-info/METADATA
inferiallm-1.0.7.dist-info/WHEEL
inferiallm-1.0.7.dist-info/entry_points.txt
inferiallm-1.0.7.dist-info/top_level.txt
inferiallm-1.0.7.dist-info/RECORD
