Metadata-Version: 2.4
Name: inferiallm
Version: 1.0.7
Summary: InferiaLLM: distributed inference, filtration, and compute orchestration platform
Author: Inferia AI
License: Business Source License 1.1
Project-URL: Repository, https://github.com/InferiaAI/InferiaLLM
Project-URL: Documentation, https://docs.inferia.ai/docs
Requires-Python: >=3.10
License-File: LICENSE
Requires-Dist: fastapi==0.109.0
Requires-Dist: uvicorn[standard]<0.30,>=0.27
Requires-Dist: httpx>=0.27.0
Requires-Dist: aiohttp>=3.8.5
Requires-Dist: grpcio==1.76.0
Requires-Dist: grpcio-tools==1.76.0
Requires-Dist: protobuf<7.0.0,>=6.31.1
Requires-Dist: anyio>=4.0
Requires-Dist: pydantic>=2.0
Requires-Dist: pydantic-settings>=2.0
Requires-Dist: email-validator>=2.1.0
Requires-Dist: python-jose[cryptography]
Requires-Dist: passlib[bcrypt]
Requires-Dist: bcrypt
Requires-Dist: pyotp
Requires-Dist: qrcode
Requires-Dist: pillow
Requires-Dist: asyncpg==0.31.0
Requires-Dist: psycopg2-binary==2.9.11
Requires-Dist: redis>=5.0
Requires-Dist: sqlalchemy>=2.0
Requires-Dist: alembic>=1.13
Requires-Dist: greenlet
Requires-Dist: jinja2
Requires-Dist: numpy
Requires-Dist: transformers>=4.40
Requires-Dist: tokenizers>=0.21
Requires-Dist: chromadb
Requires-Dist: llm-guard
Requires-Dist: presidio-analyzer
Requires-Dist: spacy
Requires-Dist: pypdf
Requires-Dist: python-docx
Requires-Dist: requests
Requires-Dist: groq
Requires-Dist: prometheus-client
Requires-Dist: python-dotenv
Requires-Dist: base58==2.1.1
Requires-Dist: pynacl
Requires-Dist: cachetools
Requires-Dist: python-multipart
Requires-Dist: skypilot
Requires-Dist: kubernetes==33.1.0
Requires-Dist: sqlalchemy>=2.0
Requires-Dist: alembic>=1.13
Requires-Dist: greenlet
Requires-Dist: jinja2
Provides-Extra: aws
Requires-Dist: boto3==1.42.10; extra == "aws"
Requires-Dist: skypilot[aws]; extra == "aws"
Provides-Extra: gcp
Requires-Dist: skypilot[gcp]; extra == "gcp"
Provides-Extra: azure
Requires-Dist: skypilot[azure]; extra == "azure"
Provides-Extra: lambda
Requires-Dist: skypilot[lambda]; extra == "lambda"
Provides-Extra: runpod
Requires-Dist: skypilot[runpod]; extra == "runpod"
Provides-Extra: all-providers
Requires-Dist: boto3==1.42.10; extra == "all-providers"
Requires-Dist: skypilot[aws,azure,gcp,kubernetes,lambda,runpod]; extra == "all-providers"
Provides-Extra: dev
Requires-Dist: pytest>=8.0; extra == "dev"
Requires-Dist: pytest-cov; extra == "dev"
Requires-Dist: pytest-asyncio>=0.23; extra == "dev"
Requires-Dist: pytest-mock; extra == "dev"
Requires-Dist: pytest-trio; extra == "dev"
Requires-Dist: pytest-twisted; extra == "dev"
Requires-Dist: pytest-tornasync; extra == "dev"
Dynamic: license-file
